inq/__init__.py
inq/__main__.py
inq/cli.py
inq/utils/currency.py
inq-0.0.1a1.dist-info/LICENSE
inq-0.0.1a1.dist-info/METADATA
inq-0.0.1a1.dist-info/WHEEL
inq-0.0.1a1.dist-info/entry_points.txt
inq-0.0.1a1.dist-info/top_level.txt
inq-0.0.1a1.dist-info/RECORD
