Metadata-Version: 2.1
Name: inq
Version: 0.0.1a1
Summary: General-purpose CLI utility
License: MIT License
Project-URL: repository, https://github.com/James-Ansley/inq
Classifier: Development Status :: 1 - Planning
Classifier: Topic :: Utilities
Classifier: Programming Language :: Python :: 3
Classifier: License :: OSI Approved :: MIT License
Requires-Python: >=3.11
License-File: LICENSE
Requires-Dist: requests >=2.31.0
